ojsterminalbio/.gitignore
ojsterminalbio/README.md
ojsterminalbio/__init__.py
ojsterminalbio/auth.py
ojsterminalbio/cli.py
ojsterminalbio/config.py
ojsterminalbio/database.py
ojsterminalbio/main.py
ojsterminalbio/run.bat
ojsterminalbio/run.sh
ojsterminalbio/schemas.py
ojsterminalbio/setup.bat
ojsterminalbio/setup.sh
ojsterminalbio/assets/custom_section_editor.js
ojsterminalbio/assets/page_editor.js
ojsterminalbio/models/__init__.py
ojsterminalbio/models/award.py
ojsterminalbio/models/course.py
ojsterminalbio/models/custom_section.py
ojsterminalbio/models/custom_section_item.py
ojsterminalbio/models/education.py
ojsterminalbio/models/experience.py
ojsterminalbio/models/page.py
ojsterminalbio/models/profile.py
ojsterminalbio/models/profile_link.py
ojsterminalbio/models/project.py
ojsterminalbio/models/publication.py
ojsterminalbio/models/research_area.py
ojsterminalbio/models/student.py
ojsterminalbio/models/user.py
ojsterminalbio/routers/__init__.py
ojsterminalbio/routers/admin.py
ojsterminalbio/routers/public.py
ojsterminalbio/screenshots/admin_dashboard.png
ojsterminalbio/screenshots/admin_profile.png
ojsterminalbio/screenshots/home.png
ojsterminalbio/screenshots/page_editor.png
ojsterminalbio/static/css/tailwind.css
ojsterminalbio/static/src/input.css
ojsterminalbio/templates/admin/base.html
ojsterminalbio/templates/admin/courses.html
ojsterminalbio/templates/admin/custom_section_editor.html
ojsterminalbio/templates/admin/dashboard.html
ojsterminalbio/templates/admin/login.html
ojsterminalbio/templates/admin/page_editor.html
ojsterminalbio/templates/admin/pages.html
ojsterminalbio/templates/admin/profile.html
ojsterminalbio/templates/admin/projects.html
ojsterminalbio/templates/admin/publications.html
ojsterminalbio/templates/admin/settings.html
ojsterminalbio/templates/admin/students.html
ojsterminalbio/templates/admin/users.html
ojsterminalbio/templates/public/about.html
ojsterminalbio/templates/public/base.html
ojsterminalbio/templates/public/index.html
ojsterminalbio-0.1.6.dist-info/METADATA
ojsterminalbio-0.1.6.dist-info/WHEEL
ojsterminalbio-0.1.6.dist-info/entry_points.txt
ojsterminalbio-0.1.6.dist-info/licenses/LICENSE
ojsterminalbio-0.1.6.dist-info/RECORD
