Metadata-Version: 2.4
Name: ojsTerminalBio
Version: 0.1.6
Summary: Academic portfolio CMS backend - pip-installable FastAPI library
Project-URL: Homepage, https://github.com/Okramjimmy/ojsTerminalBio
Project-URL: Documentation, https://github.com/Okramjimmy/ojsTerminalBio#readme
Project-URL: Repository, https://github.com/Okramjimmy/ojsTerminalBio.git
Project-URL: Issues, https://github.com/Okramjimmy/ojsTerminalBio/issues
Author-email: Okram Jimmy Singh <jimmy.lamzing@gmail.com>
License: MIT
License-File: LICENSE
Keywords: academic,backend,cms,fastapi,portfolio
Classifier: Development Status :: 4 - Beta
Classifier: Framework :: FastAPI
Classifier: Intended Audience :: Developers
Classifier: License :: OSI Approved :: MIT License
Classifier: Programming Language :: Python :: 3.10
Classifier: Programming Language :: Python :: 3.11
Classifier: Programming Language :: Python :: 3.12
Classifier: Topic :: Internet :: WWW/HTTP :: Dynamic Content :: Content Management System
Requires-Python: >=3.10
Requires-Dist: aiofiles>=23.0
Requires-Dist: email-validator>=2.1
Requires-Dist: fastapi>=0.104
Requires-Dist: jinja2>=3.1
Requires-Dist: passlib[bcrypt]>=1.7
Requires-Dist: pydantic-settings>=2.0
Requires-Dist: python-jose[cryptography]>=3.3
Requires-Dist: python-multipart>=0.0.6
Requires-Dist: sqlalchemy>=2.0
Requires-Dist: uvicorn[standard]>=0.24
Provides-Extra: dev
Requires-Dist: httpx>=0.25; extra == 'dev'
Requires-Dist: mypy>=1.0; extra == 'dev'
Requires-Dist: pytest>=7.0; extra == 'dev'
Requires-Dist: ruff>=0.1; extra == 'dev'
